{
  "miniprogramRoot": "miniprogram/",
  "cloudfunctionRoot": "cloudfunctions/",
  "setting": {
    "urlCheck": false,
    "es6": true,
    "enhance": false,
    "postcss": true,
    "preloadBackgroundData": false,
    "minified": true,
    "newFeature": false,
    "coverView": true,
    "nodeModules": false,
    "autoAudits": false,
    "showShadowRootInWxmlPanel": true,
    "scopeDataCheck": false,
    "uglifyFileName": false,
    "checkInvalidKey": true,
    "checkSiteMap": true,
    "uploadWithSourceMap": true,
    "compileHotReLoad": false,
    "useMultiFrameRuntime": true,
    "useApiHook": true,
    "useApiHostProcess": false,
    "babelSetting": {
      "ignore": [],
      "disablePlugins": [],
      "outputPath": ""
    },
    "enableEngineNative": false,
    "useIsolateContext": true,
    "userConfirmedBundleSwitch": false,
    "packNpmManually": false,
    "packNpmRelationList": [],
    "minifyWXSS": true,
    "showES6CompileOption": false
  },
  "appid": "wxe736f2d6ba8638ad",
  "projectname": "%E5%95%86%E5%9F%8E-%E4%BA%91%E5%BC%80%E5%8F%91",
  "libVersion": "2.18.0",
  "simulatorType": "wechat",
  "simulatorPluginLibVersion": {},
  "cloudfunctionTemplateRoot": "cloudfunctionTemplate",
  "condition": {
    "search": {
      "list": []
    },
    "conversation": {
      "list": []
    },
    "plugin": {
      "list": []
    },
    "game": {
      "list": []
    },
    "gamePlugin": {
      "list": []
    },
    "miniprogram": {}
  }
}